here_map_widget_ext/__init__.py
here_map_widget_ext/_version.py
here_map_widget_ext/configs.py
here_map_widget_ext/map.py
here_map_widget_ext/labextension/package.json
here_map_widget_ext/labextension/static/06398bec2a4a24629c73517760927f57.png
here_map_widget_ext/labextension/static/1eb2198bcb02edfa1389bb2edd400fd8.png
here_map_widget_ext/labextension/static/261.d4c162e5423de1023ec2.js
here_map_widget_ext/labextension/static/271.c4271097051ce91d3c2d.js
here_map_widget_ext/labextension/static/349.1b43c2832f496e73da3e.js
here_map_widget_ext/labextension/static/349.1b43c2832f496e73da3e.js.LICENSE.txt
here_map_widget_ext/labextension/static/378.f71dfacfd2bfc7d126dd.js
here_map_widget_ext/labextension/static/444.b5606cb82ffcf0fd1716.js
here_map_widget_ext/labextension/static/486.c09e2058e85ad3704fed.js
here_map_widget_ext/labextension/static/486.c09e2058e85ad3704fed.js.LICENSE.txt
here_map_widget_ext/labextension/static/522.10b5bd8ac317eeb440bd.js
here_map_widget_ext/labextension/static/522.10b5bd8ac317eeb440bd.js.LICENSE.txt
here_map_widget_ext/labextension/static/536.3a3833d02b5599d0cbe8.js
here_map_widget_ext/labextension/static/536.3a3833d02b5599d0cbe8.js.LICENSE.txt
here_map_widget_ext/labextension/static/549b33bab7247b619c0292995f5a906b.png
here_map_widget_ext/labextension/static/568.25f3a70e1ddf0dbdc190.js
here_map_widget_ext/labextension/static/69fbc9c24b3665b801445c9bccc7017d.png
here_map_widget_ext/labextension/static/f9b7a75b186911a1b04d08f8db305b7a.gif
here_map_widget_ext/labextension/static/remoteEntry.76d80b3d7b4effef2d67.js
here_map_widget_ext/labextension/static/style.js
here_map_widget_ext/labextension/static/third-party-licenses.json
here_map_widget_ext/nbextension/06398bec2a4a24629c73517760927f57.png
here_map_widget_ext/nbextension/1eb2198bcb02edfa1389bb2edd400fd8.png
here_map_widget_ext/nbextension/549b33bab7247b619c0292995f5a906b.png
here_map_widget_ext/nbextension/69fbc9c24b3665b801445c9bccc7017d.png
here_map_widget_ext/nbextension/extension.js
here_map_widget_ext_for_jupyter-0.0.2.dist-info/LICENSE
here_map_widget_ext_for_jupyter-0.0.2.dist-info/METADATA
here_map_widget_ext_for_jupyter-0.0.2.dist-info/WHEEL
here_map_widget_ext_for_jupyter-0.0.2.dist-info/top_level.txt
here_map_widget_ext_for_jupyter-0.0.2.dist-info/RECORD
